temper_std/__init__.py
temper_std/__init__.py.map
temper_std/json.py
temper_std/json.py.map
temper_std/net.py
temper_std/net.py.map
temper_std/regex.py
temper_std/regex.py.map
temper_std/temporal.py
temper_std/temporal.py.map
temper_std/testing.py
temper_std/testing.py.map
temper_std-0.6.0.dist-info/METADATA
temper_std-0.6.0.dist-info/WHEEL
temper_std-0.6.0.dist-info/RECORD
