Metadata-Version: 2.4
Name: temper-std
Version: 0.6.0
Summary: Optional support library provided with Temper
Author: Temper Contributors
License: Apache-2.0 OR MIT
Requires-Python: >=3.11
Requires-Dist: temper-core==0.6.0
